rrcgeoviz/GeneratedData.py
rrcgeoviz/GeoVizPanelDashboard.py
rrcgeoviz/JsonCreator.py
rrcgeoviz/__init__.py
rrcgeoviz/arguments.py
rrcgeoviz/geoviz_cli.py
rrcgeoviz/JsonCreatorClasses/Blocks/ArrayTextBox.py
rrcgeoviz/JsonCreatorClasses/Blocks/BaseBlock.py
rrcgeoviz/JsonCreatorClasses/Blocks/DownloadButton.py
rrcgeoviz/JsonCreatorClasses/Blocks/ImageCheckbox.py
rrcgeoviz/JsonCreatorClasses/Blocks/TextBox.py
rrcgeoviz/JsonCreatorClasses/Blocks/Toggle.py
rrcgeoviz/JsonCreatorClasses/Sections/BaseSection.py
rrcgeoviz/JsonCreatorClasses/Sections/CacheSetter.py
rrcgeoviz/JsonCreatorClasses/Sections/ColumnSetter.py
rrcgeoviz/JsonCreatorClasses/Sections/DownloadSection.py
rrcgeoviz/JsonCreatorClasses/Sections/FeatureCustomizationsSetter.py
rrcgeoviz/JsonCreatorClasses/Sections/FeatureSetter.py
rrcgeoviz/datagenerators/GeneratorBertopic.py
rrcgeoviz/datagenerators/GeneratorExample.py
rrcgeoviz/datagenerators/GeneratorPOI.py
rrcgeoviz/datagenerators/ParentDataGenerator.py
rrcgeoviz/datagenerators/data/ports.csv
rrcgeoviz/features/Downloadables.py
rrcgeoviz/features/FeartureDataFrameEditor.py
rrcgeoviz/features/FeatureAllMonths.py
rrcgeoviz/features/FeatureBertMap.py
rrcgeoviz/features/FeatureBertopic.py
rrcgeoviz/features/FeatureHeatmap.py
rrcgeoviz/features/FeatureOneYear.py
rrcgeoviz/features/FeatureOneYearMonths.py
rrcgeoviz/features/FeaturePOI.py
rrcgeoviz/features/FeatureSearch.py
rrcgeoviz/features/FeatureThreeD.py
rrcgeoviz/features/FeatureWordCloud.py
rrcgeoviz/features/FeatureYearlyRange.py
rrcgeoviz/features/HelpfulFunctions.py
rrcgeoviz/features/ParentGeovizFeature.py
rrcgeoviz-0.1.5.dist-info/METADATA
rrcgeoviz-0.1.5.dist-info/WHEEL
rrcgeoviz-0.1.5.dist-info/entry_points.txt
rrcgeoviz-0.1.5.dist-info/top_level.txt
rrcgeoviz-0.1.5.dist-info/RECORD
