Metadata-Version: 2.1
Name: rrcgeoviz
Version: 0.1.5
Summary: EDA tool for spatio-temporal data
Author-email: Jonas Nielsen <bobthebuilder.chfi@gmail.com>, Daniel Millward <dfmillward02@gmail.com>, Stephen Tveten  <stveten@student.byu.edu>
Project-URL: Documentation, https://rincon-geoviz.readthedocs.io/en/latest/index.html
Project-URL: Homepage, https://github.com/rrc-byu/ds-capstone-2023-2024
Requires-Python: >=3.9
Requires-Dist: ydata-profiling ==4.6.2
Requires-Dist: pandas ==2.0.3
Requires-Dist: panel ==1.3.8
Requires-Dist: numpy ==1.25.2
Requires-Dist: geolib ==1.0.7
Requires-Dist: geopandas ==0.14.1
Requires-Dist: geopy ==2.4.1
Requires-Dist: geoviews ==1.11.0
Requires-Dist: plotly ==5.19.0
Requires-Dist: hvplot ==0.9.0
Requires-Dist: contextily ==1.5.0
Requires-Dist: scikit-learn ==1.3.2
Requires-Dist: importlib ==1.0.4
Requires-Dist: bertopic ==0.16.0
Requires-Dist: nltk ==3.8.1
Requires-Dist: pycountry ==23.12.11
Requires-Dist: ipython ==8.18.1
